aoe2netapi/__init__.py
aoe2netapi/aoe2.py
aoe2netapi/constants/__init__.py
aoe2netapi/constants/game.py
aoe2netapi/constants/leaderboardid.py
aoe2netapi/models/__init__.py
aoe2netapi/models/leaderboard.py
aoe2netapi/models/matchhistory.py
aoe2netapi/models/ratinghistory.py
aoe2netapi/models/strings.py
aoe2netapi_wrapper-2.0.0.dist-info/LICENSE
aoe2netapi_wrapper-2.0.0.dist-info/METADATA
aoe2netapi_wrapper-2.0.0.dist-info/WHEEL
aoe2netapi_wrapper-2.0.0.dist-info/top_level.txt
aoe2netapi_wrapper-2.0.0.dist-info/RECORD
