Metadata-Version: 2.1
Name: aoe2netapi-wrapper
Version: 2.0.0
Summary: A simple and basic Python 3 API wrapper for the https://aoe2.net/#api API.
Home-page: https://github.com/sixP-NaraKa/aoe2net-api-wrapper
Author: sixP-NaraKa
Author-email: sixpaths-naraka@protonmail.com
License: MIT
Classifier: License :: OSI Approved :: MIT License
Classifier: Operating System :: OS Independent
Classifier: Programming Language :: Python :: 3
Requires-Python: >=3.7
License-File: LICENSE
Requires-Dist: requests (>=2.20.0)
Requires-Dist: dataclasses-json (==0.5.7)
